Metadata-Version: 2.1
Name: randomstrrang
Version: 0.0.2
Summary: generate a text string randomly
Home-page: 
Author: Patricia Greer
Author-email: patricia.greer88@outlook.com
License: MIT
Keywords: rand string
Classifier: Development Status :: 5 - Production/Stable
Classifier: Intended Audience :: Education
Classifier: Operating System :: Microsoft :: Windows :: Windows 10
Classifier: License :: OSI Approved :: MIT License
Classifier: Programming Language :: Python :: 3
License-File: LICENCE.txt
